pysdl3-0.9.10b0.dist-info/licenses/LICENSE
sdl3/SDL.py
sdl3/SDL_assert.py
sdl3/SDL_asyncio.py
sdl3/SDL_atomic.py
sdl3/SDL_audio.py
sdl3/SDL_bits.py
sdl3/SDL_blendmode.py
sdl3/SDL_camera.py
sdl3/SDL_clipboard.py
sdl3/SDL_cpuinfo.py
sdl3/SDL_dialog.py
sdl3/SDL_endian.py
sdl3/SDL_error.py
sdl3/SDL_events.py
sdl3/SDL_filesystem.py
sdl3/SDL_gamepad.py
sdl3/SDL_gpu.py
sdl3/SDL_guid.py
sdl3/SDL_haptic.py
sdl3/SDL_hidapi.py
sdl3/SDL_hints.py
sdl3/SDL_image.py
sdl3/SDL_init.py
sdl3/SDL_iostream.py
sdl3/SDL_joystick.py
sdl3/SDL_keyboard.py
sdl3/SDL_keycode.py
sdl3/SDL_loadso.py
sdl3/SDL_locale.py
sdl3/SDL_log.py
sdl3/SDL_main.py
sdl3/SDL_main_impl.py
sdl3/SDL_messagebox.py
sdl3/SDL_metal.py
sdl3/SDL_misc.py
sdl3/SDL_mixer.py
sdl3/SDL_mouse.py
sdl3/SDL_mutex.py
sdl3/SDL_net.py
sdl3/SDL_pen.py
sdl3/SDL_pixels.py
sdl3/SDL_platform.py
sdl3/SDL_power.py
sdl3/SDL_process.py
sdl3/SDL_properties.py
sdl3/SDL_rect.py
sdl3/SDL_render.py
sdl3/SDL_rtf.py
sdl3/SDL_scancode.py
sdl3/SDL_sensor.py
sdl3/SDL_shadercross.py
sdl3/SDL_stdinc.py
sdl3/SDL_storage.py
sdl3/SDL_surface.py
sdl3/SDL_system.py
sdl3/SDL_textengine.py
sdl3/SDL_thread.py
sdl3/SDL_time.py
sdl3/SDL_timer.py
sdl3/SDL_touch.py
sdl3/SDL_tray.py
sdl3/SDL_ttf.py
sdl3/SDL_version.py
sdl3/SDL_video.py
sdl3/SDL_vulkan.py
sdl3/__init__.py
sdl3/py.typed
pysdl3-0.9.10b0.dist-info/METADATA
pysdl3-0.9.10b0.dist-info/WHEEL
pysdl3-0.9.10b0.dist-info/top_level.txt
pysdl3-0.9.10b0.dist-info/RECORD
